llm_webdesign.py
llm_webdesign-0.0.1.dist-info/LICENSE
llm_webdesign-0.0.1.dist-info/METADATA
llm_webdesign-0.0.1.dist-info/WHEEL
llm_webdesign-0.0.1.dist-info/entry_points.txt
llm_webdesign-0.0.1.dist-info/top_level.txt
llm_webdesign-0.0.1.dist-info/RECORD
