Metadata-Version: 2.1
Name: llm-webdesign
Version: 0.0.1
Summary: LLM Web Designer
Author-email: Lucas Rangel Cezimbra <lucas@cezimbra.tec.br>
License: MIT
Project-URL: Homepage, https://github.com/lucasrcezimbra/llm-webdesign
Project-URL: Changelog, https://github.com/lucasrcezimbra/llm-webdesign/releases
Project-URL: Issues, https://github.com/lucasrcezimbra/llm-webdesign/issues
Project-URL: CI, https://github.com/lucasrcezimbra/llm-webdesign/actions
Classifier: License :: OSI Approved :: Apache Software License
License-File: LICENSE
Requires-Dist: llm
Provides-Extra: test
Requires-Dist: pytest; extra == "test"
Requires-Dist: pytest-mock; extra == "test"
